Seminar/ascii_type_detector.v
module ascii_type_detector(
        input [7:0] ascii_char,
        output number,
        output math_symbol,
        output start_stop
    );
    assign number = (48 <= ascii_char && ascii_char <= 57);//0123456789
    assign math_symbol = (ascii_char == 42) // *
                      || (ascii_char == 43) // +
                      || (ascii_char == 47) // /
                      || (ascii_char == 60) // <
                      || (ascii_char == 61) // =
                      || (ascii_char == 62);// >
    assign start_stop = (ascii_char == 0);

endmodule

Seminar/rk.v
module verify #(parameter UART_TX_baud, freq)  ( //!
    input clk,
    input rst,
    input [7:0] ascii_char,
    input char_valid,
    output reg sequence_valid,//!
    output reg output_strobe //!
);//!
    reg [1:0] k;
    reg fl;
    wire number, math_symbol, start_stop;

    localparam cnt_val = freq/UART_TX_baud + 1;
    reg [$clog2(freq/UART_TX_baud):0] strobe_cnt;
    reg strobe_clk;
    reg need_strobe_out;
    // reg LWV;

    localparam  IDLE        = 'b000,
                START_STOP  = 'b001,
                NUMBER      = 'b010,
                MATH_SYMBOL = 'b011,
                ERROR       = 'b100;
    reg [2:0] state;
    reg [2:0] next_state;

    ascii_type_detector ascii_detector(
        .ascii_char(ascii_char),
        .number(number),
        .math_symbol(math_symbol),
        .start_stop(start_stop)
    );

    always @(posedge clk)
        if (rst) begin
            state <= 0;//!
        end else 
            if (((state == START_STOP) && fl)||(state == ERROR)||rst||char_valid)
                case (state)
                    IDLE        : state <= start_stop ? START_STOP : IDLE;
                    START_STOP  : state <= fl//!
                                                ? IDLE
                                                :   number 
                                                    ? NUMBER
                                                    : ERROR;
                    NUMBER      : state <= k == 2//! 
                                                ?   !fl && math_symbol//!
                                                    ? MATH_SYMBOL
                                                    :   fl && start_stop//!
                                                        ? START_STOP
                                                        : ERROR
                                                :   number
                                                    ? NUMBER
                                                    : ERROR;
                    MATH_SYMBOL : state <= number ? NUMBER : ERROR;
                    default     : state <= IDLE;
                endcase

    // assign state =  ((state == START_STOP) && fl)  // Переключаем state без наличия новой буквы
    //                ||(state == ERROR)              // Переключаем state без наличия новой буквы
    //                || rst //!
    //                || /*LWV*/char_valid ? next_state : state;

    always @(posedge clk)
        if (rst) begin
            // LWV <= 0;
            k <= 0;
            strobe_clk <= 0;
            strobe_cnt <= cnt_val;
            sequence_valid <= 0;
            need_strobe_out <= 0; //!
            fl <= 0;
        end else begin
            // LWV <= char_valid;
            strobe_cnt <= strobe_cnt - 1;
            strobe_clk <= 0;//!
            if (!strobe_cnt) begin
                strobe_clk <= 1;
                strobe_cnt <= cnt_val;
            end
            if (char_valid) begin
                if (state == NUMBER)
                    k <= k + 1;
                else
                    k <= 0;
                if (state == MATH_SYMBOL)
                    fl <= 1; //!                
            end
            if ((state == ERROR || state == IDLE) && fl) begin
                fl <= 0; //!
                need_strobe_out <= 1;
                if (state == IDLE)
                    sequence_valid <= 1; //!
            end
            if (need_strobe_out && strobe_clk) begin
                //sequence_valid <= 0; //!
                need_strobe_out <= 0; //!
                output_strobe <= 1;
            end else 
                output_strobe <= 0;
            if (sequence_valid&&!need_strobe_out) //!
                sequence_valid <= 0;
        end
endmodule

Seminar/rk_test.v
module rk_test();
    localparam UART_TX_baud = 20,
               freq = 200,
               TR = 10;
    reg clk = 0;
    reg rst;
    reg [7:0] ascii_char;
    reg ascii_valid;
    wire sequence_valid;
    wire output_strobe;
    always #1 clk = !clk;
    verify #(.UART_TX_baud(20), .freq(200)) 
        mverify ( //!
        .clk(clk),
        .rst(rst),
        .ascii_char(ascii_char),
        .char_valid(ascii_valid),
        .sequence_valid(sequence_valid),
        .output_strobe(output_strobe)
    );
    task pch(input [7:0] putchar);
        begin
            ascii_char = putchar;
            #(TR-2)
            ascii_valid = 1;
            #2
            ascii_valid = 0;
        end
	endtask

    task transmit_valid();
        begin
            #TR
            pch(0);
            pch(48);//0
            pch(49);//1
            pch(50);//2
            pch(43);//+
            pch(50);//2
            pch(49);//1
            pch(48);//0
            pch(0);
            #TR;
        end
	endtask

    task transmit_unvalid();
        begin
            #TR
            pch(0);
            pch(48);//0
            pch(49);//1
            pch(50);//2
            pch(43);//+
            pch(49);//1
            pch(48);//0
            pch(0);
            #TR;
        end
    endtask

    initial begin
        $dumpvars;
        ascii_char = 0;
        ascii_valid = 0;
        rst = 1;
        #100
        rst = 0;
        #100
        transmit_valid();
        #1000
        transmit_unvalid();
        #1000
        $finish;
    end



endmodule

Seminar/dump.vcd
$date
	Thu Apr 24 15:05:27 2025
$end
$version
	Icarus Verilog
$end
$timescale
	1s
$end
$scope module rk_test $end
$var wire 1 ! sequence_valid $end
$var wire 1 " output_strobe $end
$var parameter 32 # TR $end
$var parameter 32 $ UART_TX_baud $end
$var parameter 32 % freq $end
$var reg 8 & ascii_char [7:0] $end
$var reg 1 ' ascii_valid $end
$var reg 1 ( clk $end
$var reg 1 ) rst $end
$scope module mverify $end
$var wire 8 * ascii_char [7:0] $end
$var wire 1 ' char_valid $end
$var wire 1 ( clk $end
$var wire 1 ) rst $end
$var wire 1 + start_stop $end
$var wire 1 , number $end
$var wire 1 - math_symbol $end
$var parameter 32 . ERROR $end
$var parameter 32 / IDLE $end
$var parameter 32 0 MATH_SYMBOL $end
$var parameter 32 1 NUMBER $end
$var parameter 32 2 START_STOP $end
$var parameter 32 3 UART_TX_baud $end
$var parameter 33 4 cnt_val $end
$var parameter 32 5 freq $end
$var reg 1 6 fl $end
$var reg 2 7 k [1:0] $end
$var reg 1 8 need_strobe_out $end
$var reg 1 " output_strobe $end
$var reg 1 ! sequence_valid $end
$var reg 3 9 state [2:0] $end
$var reg 1 : strobe_clk $end
$var reg 5 ; strobe_cnt [4:0] $end
$scope module ascii_detector $end
$var wire 8 < ascii_char [7:0] $end
$var wire 1 - math_symbol $end
$var wire 1 , number $end
$var wire 1 + start_stop $end
$upscope $end
$upscope $end
$scope task pch $end
$var reg 8 = putchar [7:0] $end
$upscope $end
$scope task transmit_unvalid $end
$upscope $end
$scope task transmit_valid $end
$upscope $end
$upscope $end
$enddefinitions $end
$comment Show the parameter values. $end
$dumpall
b11001000 5
b1011 4
b10100 3
b1 2
b10 1
b11 0
b0 /
b100 .
b11001000 %
b10100 $
b1010 #
$end
#0
$dumpvars
bx =
b0 <
bx ;
x:
bx 9
x8
bx 7
x6
0-
0,
1+
b0 *
1)
0(
0'
b0 &
x"
x!
$end
#1
b0 9
06
08
0!
b1011 ;
0:
b0 7
1(
#2
0(
#3
1(
#4
0(
#5
1(
#6
0(
#7
1(
#8
0(
#9
1(
#10
0(
#11
1(
#12
0(
#13
1(
#14
0(
#15
1(
#16
0(
#17
1(
#18
0(
#19
1(
#20
0(
#21
1(
#22
0(
#23
1(
#24
0(
#25
1(
#26
0(
#27
1(
#28
0(
#29
1(
#30
0(
#31
1(
#32
0(
#33
1(
#34
0(
#35
1(
#36
0(
#37
1(
#38
0(
#39
1(
#40
0(
#41
1(
#42
0(
#43
1(
#44
0(
#45
1(
#46
0(
#47
1(
#48
0(
#49
1(
#50
0(
#51
1(
#52
0(
#53
1(
#54
0(
#55
1(
#56
0(
#57
1(
#58
0(
#59
1(
#60
0(
#61
1(
#62
0(
#63
1(
#64
0(
#65
1(
#66
0(
#67
1(
#68
0(
#69
1(
#70
0(
#71
1(
#72
0(
#73
1(
#74
0(
#75
1(
#76
0(
#77
1(
#78
0(
#79
1(
#80
0(
#81
1(
#82
0(
#83
1(
#84
0(
#85
1(
#86
0(
#87
1(
#88
0(
#89
1(
#90
0(
#91
1(
#92
0(
#93
1(
#94
0(
#95
1(
#96
0(
#97
1(
#98
0(
#99
1(
#100
0(
0)
#101
0"
b1010 ;
1(
#102
0(
#103
b1001 ;
1(
#104
0(
#105
b1000 ;
1(
#106
0(
#107
b111 ;
1(
#108
0(
#109
b110 ;
1(
#110
0(
#111
b101 ;
1(
#112
0(
#113
b100 ;
1(
#114
0(
#115
b11 ;
1(
#116
0(
#117
b10 ;
1(
#118
0(
#119
b1 ;
1(
#120
0(
#121
b0 ;
1(
#122
0(
#123
1:
b1011 ;
1(
#124
0(
#125
0:
b1010 ;
1(
#126
0(
#127
b1001 ;
1(
#128
0(
#129
b1000 ;
1(
#130
0(
#131
b111 ;
1(
#132
0(
#133
b110 ;
1(
#134
0(
#135
b101 ;
1(
#136
0(
#137
b100 ;
1(
#138
0(
#139
b11 ;
1(
#140
0(
#141
b10 ;
1(
#142
0(
#143
b1 ;
1(
#144
0(
#145
b0 ;
1(
#146
0(
#147
1:
b1011 ;
1(
#148
0(
#149
0:
b1010 ;
1(
#150
0(
#151
b1001 ;
1(
#152
0(
#153
b1000 ;
1(
#154
0(
#155
b111 ;
1(
#156
0(
#157
b110 ;
1(
#158
0(
#159
b101 ;
1(
#160
0(
#161
b100 ;
1(
#162
0(
#163
b11 ;
1(
#164
0(
#165
b10 ;
1(
#166
0(
#167
b1 ;
1(
#168
0(
#169
b0 ;
1(
#170
0(
#171
1:
b1011 ;
1(
#172
0(
#173
0:
b1010 ;
1(
#174
0(
#175
b1001 ;
1(
#176
0(
#177
b1000 ;
1(
#178
0(
#179
b111 ;
1(
#180
0(
#181
b110 ;
1(
#182
0(
#183
b101 ;
1(
#184
0(
#185
b100 ;
1(
#186
0(
#187
b11 ;
1(
#188
0(
#189
b10 ;
1(
#190
0(
#191
b1 ;
1(
#192
0(
#193
b0 ;
1(
#194
0(
#195
1:
b1011 ;
1(
#196
0(
#197
0:
b1010 ;
1(
#198
0(
#199
b1001 ;
1(
#200
0(
#201
b1000 ;
1(
#202
0(
#203
b111 ;
1(
#204
0(
#205
b110 ;
1(
#206
0(
#207
b101 ;
1(
#208
0(
#209
b100 ;
1(
#210
0(
b0 =
#211
b11 ;
1(
#212
0(
#213
b10 ;
1(
#214
0(
#215
b1 ;
1(
#216
0(
#217
b0 ;
1(
#218
0(
1'
#219
1:
b1011 ;
b1 9
1(
#220
1,
0(
0+
b110000 &
b110000 *
b110000 <
b110000 =
0'
#221
0:
b1010 ;
1(
#222
0(
#223
b1001 ;
1(
#224
0(
#225
b1000 ;
1(
#226
0(
#227
b111 ;
1(
#228
0(
1'
#229
b10 9
b110 ;
1(
#230
0(
b110001 &
b110001 *
b110001 <
b110001 =
0'
#231
b101 ;
1(
#232
0(
#233
b100 ;
1(
#234
0(
#235
b11 ;
1(
#236
0(
#237
b10 ;
1(
#238
0(
1'
#239
b1 7
b1 ;
1(
#240
0(
b110010 &
b110010 *
b110010 <
b110010 =
0'
#241
b0 ;
1(
#242
0(
#243
1:
b1011 ;
1(
#244
0(
#245
0:
b1010 ;
1(
#246
0(
#247
b1001 ;
1(
#248
0(
1'
#249
b10 7
b1000 ;
1(
#250
1-
0,
0(
b101011 &
b101011 *
b101011 <
b101011 =
0'
#251
b111 ;
1(
#252
0(
#253
b110 ;
1(
#254
0(
#255
b101 ;
1(
#256
0(
#257
b100 ;
1(
#258
0(
1'
#259
b11 7
b11 ;
b11 9
1(
#260
0-
1,
0(
b110010 &
b110010 *
b110010 <
b110010 =
0'
#261
b10 ;
1(
#262
0(
#263
b1 ;
1(
#264
0(
#265
b0 ;
1(
#266
0(
#267
1:
b1011 ;
1(
#268
0(
1'
#269
b10 9
16
b0 7
0:
b1010 ;
1(
#270
0(
b110001 &
b110001 *
b110001 <
b110001 =
0'
#271
b1001 ;
1(
#272
0(
#273
b1000 ;
1(
#274
0(
#275
b111 ;
1(
#276
0(
#277
b110 ;
1(
#278
0(
1'
#279
b1 7
b101 ;
1(
#280
0(
b110000 &
b110000 *
b110000 <
b110000 =
0'
#281
b100 ;
1(
#282
0(
#283
b11 ;
1(
#284
0(
#285
b10 ;
1(
#286
0(
#287
b1 ;
1(
#288
0(
1'
#289
b10 7
b0 ;
1(
#290
0,
0(
1+
b0 &
b0 *
b0 <
b0 =
0'
#291
1:
b1011 ;
1(
#292
0(
#293
0:
b1010 ;
1(
#294
0(
#295
b1001 ;
1(
#296
0(
#297
b1000 ;
1(
#298
0(
1'
#299
b11 7
b111 ;
b1 9
1(
#300
0(
0'
#301
b0 9
b110 ;
1(
#302
0(
#303
1!
18
06
b101 ;
1(
#304
0(
#305
b100 ;
1(
#306
0(
#307
b11 ;
1(
#308
0(
#309
b10 ;
1(
#310
0(
#311
b1 ;
1(
#312
0(
#313
b0 ;
1(
#314
0(
#315
1:
b1011 ;
1(
#316
0(
#317
1"
08
0:
b1010 ;
1(
#318
0(
#319
0!
0"
b1001 ;
1(
#320
0(
#321
b1000 ;
1(
#322
0(
#323
b111 ;
1(
#324
0(
#325
b110 ;
1(
#326
0(
#327
b101 ;
1(
#328
0(
#329
b100 ;
1(
#330
0(
#331
b11 ;
1(
#332
0(
#333
b10 ;
1(
#334
0(
#335
b1 ;
1(
#336
0(
#337
b0 ;
1(
#338
0(
#339
1:
b1011 ;
1(
#340
0(
#341
0:
b1010 ;
1(
#342
0(
#343
b1001 ;
1(
#344
0(
#345
b1000 ;
1(
#346
0(
#347
b111 ;
1(
#348
0(
#349
b110 ;
1(
#350
0(
#351
b101 ;
1(
#352
0(
#353
b100 ;
1(
#354
0(
#355
b11 ;
1(
#356
0(
#357
b10 ;
1(
#358
0(
#359
b1 ;
1(
#360
0(
#361
b0 ;
1(
#362
0(
#363
1:
b1011 ;
1(
#364
0(
#365
0:
b1010 ;
1(
#366
0(
#367
b1001 ;
1(
#368
0(
#369
b1000 ;
1(
#370
0(
#371
b111 ;
1(
#372
0(
#373
b110 ;
1(
#374
0(
#375
b101 ;
1(
#376
0(
#377
b100 ;
1(
#378
0(
#379
b11 ;
1(
#380
0(
#381
b10 ;
1(
#382
0(
#383
b1 ;
1(
#384
0(
#385
b0 ;
1(
#386
0(
#387
1:
b1011 ;
1(
#388
0(
#389
0:
b1010 ;
1(
#390
0(
#391
b1001 ;
1(
#392
0(
#393
b1000 ;
1(
#394
0(
#395
b111 ;
1(
#396
0(
#397
b110 ;
1(
#398
0(
#399
b101 ;
1(
#400
0(
#401
b100 ;
1(
#402
0(
#403
b11 ;
1(
#404
0(
#405
b10 ;
1(
#406
0(
#407
b1 ;
1(
#408
0(
#409
b0 ;
1(
#410
0(
#411
1:
b1011 ;
1(
#412
0(
#413
0:
b1010 ;
1(
#414
0(
#415
b1001 ;
1(
#416
0(
#417
b1000 ;
1(
#418
0(
#419
b111 ;
1(
#420
0(
#421
b110 ;
1(
#422
0(
#423
b101 ;
1(
#424
0(
#425
b100 ;
1(
#426
0(
#427
b11 ;
1(
#428
0(
#429
b10 ;
1(
#430
0(
#431
b1 ;
1(
#432
0(
#433
b0 ;
1(
#434
0(
#435
1:
b1011 ;
1(
#436
0(
#437
0:
b1010 ;
1(
#438
0(
#439
b1001 ;
1(
#440
0(
#441
b1000 ;
1(
#442
0(
#443
b111 ;
1(
#444
0(
#445
b110 ;
1(
#446
0(
#447
b101 ;
1(
#448
0(
#449
b100 ;
1(
#450
0(
#451
b11 ;
1(
#452
0(
#453
b10 ;
1(
#454
0(
#455
b1 ;
1(
#456
0(
#457
b0 ;
1(
#458
0(
#459
1:
b1011 ;
1(
#460
0(
#461
0:
b1010 ;
1(
#462
0(
#463
b1001 ;
1(
#464
0(
#465
b1000 ;
1(
#466
0(
#467
b111 ;
1(
#468
0(
#469
b110 ;
1(
#470
0(
#471
b101 ;
1(
#472
0(
#473
b100 ;
1(
#474
0(
#475
b11 ;
1(
#476
0(
#477
b10 ;
1(
#478
0(
#479
b1 ;
1(
#480
0(
#481
b0 ;
1(
#482
0(
#483
1:
b1011 ;
1(
#484
0(
#485
0:
b1010 ;
1(
#486
0(
#487
b1001 ;
1(
#488
0(
#489
b1000 ;
1(
#490
0(
#491
b111 ;
1(
#492
0(
#493
b110 ;
1(
#494
0(
#495
b101 ;
1(
#496
0(
#497
b100 ;
1(
#498
0(
#499
b11 ;
1(
#500
0(
#501
b10 ;
1(
#502
0(
#503
b1 ;
1(
#504
0(
#505
b0 ;
1(
#506
0(
#507
1:
b1011 ;
1(
#508
0(
#509
0:
b1010 ;
1(
#510
0(
#511
b1001 ;
1(
#512
0(
#513
b1000 ;
1(
#514
0(
#515
b111 ;
1(
#516
0(
#517
b110 ;
1(
#518
0(
#519
b101 ;
1(
#520
0(
#521
b100 ;
1(
#522
0(
#523
b11 ;
1(
#524
0(
#525
b10 ;
1(
#526
0(
#527
b1 ;
1(
#528
0(
#529
b0 ;
1(
#530
0(
#531
1:
b1011 ;
1(
#532
0(
#533
0:
b1010 ;
1(
#534
0(
#535
b1001 ;
1(
#536
0(
#537
b1000 ;
1(
#538
0(
#539
b111 ;
1(
#540
0(
#541
b110 ;
1(
#542
0(
#543
b101 ;
1(
#544
0(
#545
b100 ;
1(
#546
0(
#547
b11 ;
1(
#548
0(
#549
b10 ;
1(
#550
0(
#551
b1 ;
1(
#552
0(
#553
b0 ;
1(
#554
0(
#555
1:
b1011 ;
1(
#556
0(
#557
0:
b1010 ;
1(
#558
0(
#559
b1001 ;
1(
#560
0(
#561
b1000 ;
1(
#562
0(
#563
b111 ;
1(
#564
0(
#565
b110 ;
1(
#566
0(
#567
b101 ;
1(
#568
0(
#569
b100 ;
1(
#570
0(
#571
b11 ;
1(
#572
0(
#573
b10 ;
1(
#574
0(
#575
b1 ;
1(
#576
0(
#577
b0 ;
1(
#578
0(
#579
1:
b1011 ;
1(
#580
0(
#581
0:
b1010 ;
1(
#582
0(
#583
b1001 ;
1(
#584
0(
#585
b1000 ;
1(
#586
0(
#587
b111 ;
1(
#588
0(
#589
b110 ;
1(
#590
0(
#591
b101 ;
1(
#592
0(
#593
b100 ;
1(
#594
0(
#595
b11 ;
1(
#596
0(
#597
b10 ;
1(
#598
0(
#599
b1 ;
1(
#600
0(
#601
b0 ;
1(
#602
0(
#603
1:
b1011 ;
1(
#604
0(
#605
0:
b1010 ;
1(
#606
0(
#607
b1001 ;
1(
#608
0(
#609
b1000 ;
1(
#610
0(
#611
b111 ;
1(
#612
0(
#613
b110 ;
1(
#614
0(
#615
b101 ;
1(
#616
0(
#617
b100 ;
1(
#618
0(
#619
b11 ;
1(
#620
0(
#621
b10 ;
1(
#622
0(
#623
b1 ;
1(
#624
0(
#625
b0 ;
1(
#626
0(
#627
1:
b1011 ;
1(
#628
0(
#629
0:
b1010 ;
1(
#630
0(
#631
b1001 ;
1(
#632
0(
#633
b1000 ;
1(
#634
0(
#635
b111 ;
1(
#636
0(
#637
b110 ;
1(
#638
0(
#639
b101 ;
1(
#640
0(
#641
b100 ;
1(
#642
0(
#643
b11 ;
1(
#644
0(
#645
b10 ;
1(
#646
0(
#647
b1 ;
1(
#648
0(
#649
b0 ;
1(
#650
0(
#651
1:
b1011 ;
1(
#652
0(
#653
0:
b1010 ;
1(
#654
0(
#655
b1001 ;
1(
#656
0(
#657
b1000 ;
1(
#658
0(
#659
b111 ;
1(
#660
0(
#661
b110 ;
1(
#662
0(
#663
b101 ;
1(
#664
0(
#665
b100 ;
1(
#666
0(
#667
b11 ;
1(
#668
0(
#669
b10 ;
1(
#670
0(
#671
b1 ;
1(
#672
0(
#673
b0 ;
1(
#674
0(
#675
1:
b1011 ;
1(
#676
0(
#677
0:
b1010 ;
1(
#678
0(
#679
b1001 ;
1(
#680
0(
#681
b1000 ;
1(
#682
0(
#683
b111 ;
1(
#684
0(
#685
b110 ;
1(
#686
0(
#687
b101 ;
1(
#688
0(
#689
b100 ;
1(
#690
0(
#691
b11 ;
1(
#692
0(
#693
b10 ;
1(
#694
0(
#695
b1 ;
1(
#696
0(
#697
b0 ;
1(
#698
0(
#699
1:
b1011 ;
1(
#700
0(
#701
0:
b1010 ;
1(
#702
0(
#703
b1001 ;
1(
#704
0(
#705
b1000 ;
1(
#706
0(
#707
b111 ;
1(
#708
0(
#709
b110 ;
1(
#710
0(
#711
b101 ;
1(
#712
0(
#713
b100 ;
1(
#714
0(
#715
b11 ;
1(
#716
0(
#717
b10 ;
1(
#718
0(
#719
b1 ;
1(
#720
0(
#721
b0 ;
1(
#722
0(
#723
1:
b1011 ;
1(
#724
0(
#725
0:
b1010 ;
1(
#726
0(
#727
b1001 ;
1(
#728
0(
#729
b1000 ;
1(
#730
0(
#731
b111 ;
1(
#732
0(
#733
b110 ;
1(
#734
0(
#735
b101 ;
1(
#736
0(
#737
b100 ;
1(
#738
0(
#739
b11 ;
1(
#740
0(
#741
b10 ;
1(
#742
0(
#743
b1 ;
1(
#744
0(
#745
b0 ;
1(
#746
0(
#747
1:
b1011 ;
1(
#748
0(
#749
0:
b1010 ;
1(
#750
0(
#751
b1001 ;
1(
#752
0(
#753
b1000 ;
1(
#754
0(
#755
b111 ;
1(
#756
0(
#757
b110 ;
1(
#758
0(
#759
b101 ;
1(
#760
0(
#761
b100 ;
1(
#762
0(
#763
b11 ;
1(
#764
0(
#765
b10 ;
1(
#766
0(
#767
b1 ;
1(
#768
0(
#769
b0 ;
1(
#770
0(
#771
1:
b1011 ;
1(
#772
0(
#773
0:
b1010 ;
1(
#774
0(
#775
b1001 ;
1(
#776
0(
#777
b1000 ;
1(
#778
0(
#779
b111 ;
1(
#780
0(
#781
b110 ;
1(
#782
0(
#783
b101 ;
1(
#784
0(
#785
b100 ;
1(
#786
0(
#787
b11 ;
1(
#788
0(
#789
b10 ;
1(
#790
0(
#791
b1 ;
1(
#792
0(
#793
b0 ;
1(
#794
0(
#795
1:
b1011 ;
1(
#796
0(
#797
0:
b1010 ;
1(
#798
0(
#799
b1001 ;
1(
#800
0(
#801
b1000 ;
1(
#802
0(
#803
b111 ;
1(
#804
0(
#805
b110 ;
1(
#806
0(
#807
b101 ;
1(
#808
0(
#809
b100 ;
1(
#810
0(
#811
b11 ;
1(
#812
0(
#813
b10 ;
1(
#814
0(
#815
b1 ;
1(
#816
0(
#817
b0 ;
1(
#818
0(
#819
1:
b1011 ;
1(
#820
0(
#821
0:
b1010 ;
1(
#822
0(
#823
b1001 ;
1(
#824
0(
#825
b1000 ;
1(
#826
0(
#827
b111 ;
1(
#828
0(
#829
b110 ;
1(
#830
0(
#831
b101 ;
1(
#832
0(
#833
b100 ;
1(
#834
0(
#835
b11 ;
1(
#836
0(
#837
b10 ;
1(
#838
0(
#839
b1 ;
1(
#840
0(
#841
b0 ;
1(
#842
0(
#843
1:
b1011 ;
1(
#844
0(
#845
0:
b1010 ;
1(
#846
0(
#847
b1001 ;
1(
#848
0(
#849
b1000 ;
1(
#850
0(
#851
b111 ;
1(
#852
0(
#853
b110 ;
1(
#854
0(
#855
b101 ;
1(
#856
0(
#857
b100 ;
1(
#858
0(
#859
b11 ;
1(
#860
0(
#861
b10 ;
1(
#862
0(
#863
b1 ;
1(
#864
0(
#865
b0 ;
1(
#866
0(
#867
1:
b1011 ;
1(
#868
0(
#869
0:
b1010 ;
1(
#870
0(
#871
b1001 ;
1(
#872
0(
#873
b1000 ;
1(
#874
0(
#875
b111 ;
1(
#876
0(
#877
b110 ;
1(
#878
0(
#879
b101 ;
1(
#880
0(
#881
b100 ;
1(
#882
0(
#883
b11 ;
1(
#884
0(
#885
b10 ;
1(
#886
0(
#887
b1 ;
1(
#888
0(
#889
b0 ;
1(
#890
0(
#891
1:
b1011 ;
1(
#892
0(
#893
0:
b1010 ;
1(
#894
0(
#895
b1001 ;
1(
#896
0(
#897
b1000 ;
1(
#898
0(
#899
b111 ;
1(
#900
0(
#901
b110 ;
1(
#902
0(
#903
b101 ;
1(
#904
0(
#905
b100 ;
1(
#906
0(
#907
b11 ;
1(
#908
0(
#909
b10 ;
1(
#910
0(
#911
b1 ;
1(
#912
0(
#913
b0 ;
1(
#914
0(
#915
1:
b1011 ;
1(
#916
0(
#917
0:
b1010 ;
1(
#918
0(
#919
b1001 ;
1(
#920
0(
#921
b1000 ;
1(
#922
0(
#923
b111 ;
1(
#924
0(
#925
b110 ;
1(
#926
0(
#927
b101 ;
1(
#928
0(
#929
b100 ;
1(
#930
0(
#931
b11 ;
1(
#932
0(
#933
b10 ;
1(
#934
0(
#935
b1 ;
1(
#936
0(
#937
b0 ;
1(
#938
0(
#939
1:
b1011 ;
1(
#940
0(
#941
0:
b1010 ;
1(
#942
0(
#943
b1001 ;
1(
#944
0(
#945
b1000 ;
1(
#946
0(
#947
b111 ;
1(
#948
0(
#949
b110 ;
1(
#950
0(
#951
b101 ;
1(
#952
0(
#953
b100 ;
1(
#954
0(
#955
b11 ;
1(
#956
0(
#957
b10 ;
1(
#958
0(
#959
b1 ;
1(
#960
0(
#961
b0 ;
1(
#962
0(
#963
1:
b1011 ;
1(
#964
0(
#965
0:
b1010 ;
1(
#966
0(
#967
b1001 ;
1(
#968
0(
#969
b1000 ;
1(
#970
0(
#971
b111 ;
1(
#972
0(
#973
b110 ;
1(
#974
0(
#975
b101 ;
1(
#976
0(
#977
b100 ;
1(
#978
0(
#979
b11 ;
1(
#980
0(
#981
b10 ;
1(
#982
0(
#983
b1 ;
1(
#984
0(
#985
b0 ;
1(
#986
0(
#987
1:
b1011 ;
1(
#988
0(
#989
0:
b1010 ;
1(
#990
0(
#991
b1001 ;
1(
#992
0(
#993
b1000 ;
1(
#994
0(
#995
b111 ;
1(
#996
0(
#997
b110 ;
1(
#998
0(
#999
b101 ;
1(
#1000
0(
#1001
b100 ;
1(
#1002
0(
#1003
b11 ;
1(
#1004
0(
#1005
b10 ;
1(
#1006
0(
#1007
b1 ;
1(
#1008
0(
#1009
b0 ;
1(
#1010
0(
#1011
1:
b1011 ;
1(
#1012
0(
#1013
0:
b1010 ;
1(
#1014
0(
#1015
b1001 ;
1(
#1016
0(
#1017
b1000 ;
1(
#1018
0(
#1019
b111 ;
1(
#1020
0(
#1021
b110 ;
1(
#1022
0(
#1023
b101 ;
1(
#1024
0(
#1025
b100 ;
1(
#1026
0(
#1027
b11 ;
1(
#1028
0(
#1029
b10 ;
1(
#1030
0(
#1031
b1 ;
1(
#1032
0(
#1033
b0 ;
1(
#1034
0(
#1035
1:
b1011 ;
1(
#1036
0(
#1037
0:
b1010 ;
1(
#1038
0(
#1039
b1001 ;
1(
#1040
0(
#1041
b1000 ;
1(
#1042
0(
#1043
b111 ;
1(
#1044
0(
#1045
b110 ;
1(
#1046
0(
#1047
b101 ;
1(
#1048
0(
#1049
b100 ;
1(
#1050
0(
#1051
b11 ;
1(
#1052
0(
#1053
b10 ;
1(
#1054
0(
#1055
b1 ;
1(
#1056
0(
#1057
b0 ;
1(
#1058
0(
#1059
1:
b1011 ;
1(
#1060
0(
#1061
0:
b1010 ;
1(
#1062
0(
#1063
b1001 ;
1(
#1064
0(
#1065
b1000 ;
1(
#1066
0(
#1067
b111 ;
1(
#1068
0(
#1069
b110 ;
1(
#1070
0(
#1071
b101 ;
1(
#1072
0(
#1073
b100 ;
1(
#1074
0(
#1075
b11 ;
1(
#1076
0(
#1077
b10 ;
1(
#1078
0(
#1079
b1 ;
1(
#1080
0(
#1081
b0 ;
1(
#1082
0(
#1083
1:
b1011 ;
1(
#1084
0(
#1085
0:
b1010 ;
1(
#1086
0(
#1087
b1001 ;
1(
#1088
0(
#1089
b1000 ;
1(
#1090
0(
#1091
b111 ;
1(
#1092
0(
#1093
b110 ;
1(
#1094
0(
#1095
b101 ;
1(
#1096
0(
#1097
b100 ;
1(
#1098
0(
#1099
b11 ;
1(
#1100
0(
#1101
b10 ;
1(
#1102
0(
#1103
b1 ;
1(
#1104
0(
#1105
b0 ;
1(
#1106
0(
#1107
1:
b1011 ;
1(
#1108
0(
#1109
0:
b1010 ;
1(
#1110
0(
#1111
b1001 ;
1(
#1112
0(
#1113
b1000 ;
1(
#1114
0(
#1115
b111 ;
1(
#1116
0(
#1117
b110 ;
1(
#1118
0(
#1119
b101 ;
1(
#1120
0(
#1121
b100 ;
1(
#1122
0(
#1123
b11 ;
1(
#1124
0(
#1125
b10 ;
1(
#1126
0(
#1127
b1 ;
1(
#1128
0(
#1129
b0 ;
1(
#1130
0(
#1131
1:
b1011 ;
1(
#1132
0(
#1133
0:
b1010 ;
1(
#1134
0(
#1135
b1001 ;
1(
#1136
0(
#1137
b1000 ;
1(
#1138
0(
#1139
b111 ;
1(
#1140
0(
#1141
b110 ;
1(
#1142
0(
#1143
b101 ;
1(
#1144
0(
#1145
b100 ;
1(
#1146
0(
#1147
b11 ;
1(
#1148
0(
#1149
b10 ;
1(
#1150
0(
#1151
b1 ;
1(
#1152
0(
#1153
b0 ;
1(
#1154
0(
#1155
1:
b1011 ;
1(
#1156
0(
#1157
0:
b1010 ;
1(
#1158
0(
#1159
b1001 ;
1(
#1160
0(
#1161
b1000 ;
1(
#1162
0(
#1163
b111 ;
1(
#1164
0(
#1165
b110 ;
1(
#1166
0(
#1167
b101 ;
1(
#1168
0(
#1169
b100 ;
1(
#1170
0(
#1171
b11 ;
1(
#1172
0(
#1173
b10 ;
1(
#1174
0(
#1175
b1 ;
1(
#1176
0(
#1177
b0 ;
1(
#1178
0(
#1179
1:
b1011 ;
1(
#1180
0(
#1181
0:
b1010 ;
1(
#1182
0(
#1183
b1001 ;
1(
#1184
0(
#1185
b1000 ;
1(
#1186
0(
#1187
b111 ;
1(
#1188
0(
#1189
b110 ;
1(
#1190
0(
#1191
b101 ;
1(
#1192
0(
#1193
b100 ;
1(
#1194
0(
#1195
b11 ;
1(
#1196
0(
#1197
b10 ;
1(
#1198
0(
#1199
b1 ;
1(
#1200
0(
#1201
b0 ;
1(
#1202
0(
#1203
1:
b1011 ;
1(
#1204
0(
#1205
0:
b1010 ;
1(
#1206
0(
#1207
b1001 ;
1(
#1208
0(
#1209
b1000 ;
1(
#1210
0(
#1211
b111 ;
1(
#1212
0(
#1213
b110 ;
1(
#1214
0(
#1215
b101 ;
1(
#1216
0(
#1217
b100 ;
1(
#1218
0(
#1219
b11 ;
1(
#1220
0(
#1221
b10 ;
1(
#1222
0(
#1223
b1 ;
1(
#1224
0(
#1225
b0 ;
1(
#1226
0(
