universal_template/ascii_type_detector.v
// Данный модуль проверяет символ на совпадение с паттерном, в нем ничего менять не нкжно

module ascii_type_detector (
  input wire [7:0] ascii_char,
  output reg small_letter, // Строчная буква (a-z)
  output reg capital_letter, // Заглавная буква (A-Z)
  output reg number, // Цифра (0-9)
  output reg hex_digit, // Шестнадцатеричная цифра (0-9, A-F, a-f)
  output reg punctuation_basic, // Основные знаки препинания (., ,, :, ;, !, ?, ', ")
  output reg punctuation_finance, // Финансовые символы (#, $, %, &, @)
  output reg parentheses, // Скобки ((, ), [, ])
  output reg curly_braces, // Фигурные скобки ({, }) - добавлено
  output reg math_symbol, // Математические символы (+, -, *, /, \, =, <, >)
  output reg whitespace, // Пробельные символы (пробел, табуляция, перевод строки, возврат каретки)
  output reg vowel, //Гласные буквы [aeiouAEIOU]
  output reg consonant, // Согласные буквы 
  output reg start_stop, //Начало и конец строки (\0)
  output reg other // Другие символы
);

  always @(*) begin
    small_letter = 1'b0;
    capital_letter = 1'b0;
    number = 1'b0;
    hex_digit = 1'b0;
    punctuation_basic = 1'b0;
    punctuation_finance = 1'b0;
    parentheses = 1'b0;
    curly_braces = 1'b0;
    math_symbol = 1'b0;
    whitespace = 1'b0;
    vowel = 1'b0;
    start_stop = 1'b0;
    other = 1'b0;
    consonant = 1'b0;
    if (ascii_char >= 8'h61 && ascii_char <= 8'h7a) small_letter = 1'b1;
    if (ascii_char >= 8'h41 && ascii_char <= 8'h5a) capital_letter = 1'b1;
    if (ascii_char >= 8'h30 && ascii_char <= 8'h39) number = 1'b1;
    if (ascii_char >= 8'h41 && ascii_char <= 8'h46) hex_digit = 1'b1;
    if (ascii_char >= 8'h61 && ascii_char <= 8'h66) hex_digit = 1'b1;
    if (number)                                     hex_digit = 1'b1; // эта строка добавлена, а то 0-9 не считаютсяя hex_digit
    if (ascii_char == 8'h2E || ascii_char == 8'h2C || ascii_char == 8'h3A || ascii_char == 8'h3B || ascii_char == 8'h21 || ascii_char == 8'h3F || ascii_char == 8'h27 || ascii_char == 8'h22) punctuation_basic = 1'b1;
    if (ascii_char == 8'h23 || ascii_char == 8'h24 || ascii_char == 8'h25 || ascii_char == 8'h26 || ascii_char == 8'h40) punctuation_finance = 1'b1;
    if (ascii_char == 8'h28 || ascii_char == 8'h29 || ascii_char == 8'h5B || ascii_char == 8'h5D) parentheses = 1'b1;
    if (ascii_char == 8'h7B || ascii_char == 8'h7D) curly_braces = 1'b1;
    if (ascii_char == 8'h2B || ascii_char == 8'h2D || ascii_char == 8'h2A || ascii_char == 8'h2F || ascii_char == 8'h5C || ascii_char == 8'h3D || ascii_char == 8'h3C || ascii_char == 8'h3E) math_symbol = 1'b1;
    if (ascii_char == 8'h20 || ascii_char == 8'h09 || ascii_char == 8'h0A || ascii_char == 8'h0D) whitespace = 1'b1;
    if (ascii_char == 8'h61 || ascii_char == 8'h65 || ascii_char == 8'h69 || ascii_char == 8'h6f || ascii_char == 8'h75 || ascii_char == 8'h41 || ascii_char == 8'h45 || ascii_char == 8'h49 || ascii_char == 8'h4f || ascii_char == 8'h55) vowel = 1'b1;
    if (!(small_letter | capital_letter | number | hex_digit | punctuation_basic | punctuation_finance | parentheses | curly_braces | math_symbol | whitespace)) other = 1'b1;
    if (ascii_char == 8'h0 || ascii_char == 8'h0A) start_stop = 1'b1;
    if (((small_letter||capital_letter)&&!vowel)) consonant = 1'b1;
  end
endmodule

variants/v10/task.v
// Модуль с заданием по варианту
// Начиная с двойной черты ====== и заканчивая одинарной ------- идет код, 
// который необходимо заменить в соответствии с вариантом

module tsk(
    input [3:0] state,
    input rst,
    input clk,
    input valid,
    input error_verify,
    output reg [3:0] next_state,

    input   start_stop,         // Начало и конец строки (\0)
            small_letter,       // Строчная буква (a-z)
            capital_letter,     // Заглавная буква (A-Z)
            number,             // Цифра (0-9)
            hex_digit,          // Шестнадцатеричная цифра (0-9, A-F, a-f)
            punctuation_basic,  // Основные знаки препинания (., ,, :, ;, !, ?, ', ")
            punctuation_finance, // Финансовые символы (#, $, %, &, @)
            parentheses,        // Скобки ((, ), [, ])
            curly_braces,       // Фигурные скобки ({, }) - добавлено
            math_symbol,        // Математические символы (+, -, *, /, \, =, <, >)
            whitespace,         // Пробельные символы (пробел, табуляция, перевод строки, возврат каретки)
            vowel,              // Гласные буквы [aeiouAEIOU]
            consonant,          // Согласные буквы
            other               // Другие символы
);

    

    localparam // Общие состояния
               IDLE =  0, 
               START = 1,
               STOP =  2,
               ERROR = 3,

               // =========================================
               // Состояния автомата по варианту (4 - состояние в которое необходимо попасть со старта)
               PARENTHESES1  = 4,
               MATHSYMBOL = 5,
               NUMBER = 6,
               PARENTHESES2  = 7;
               // -----------------------------------------

    // =========================================
    // Счетчики
    reg [2:0] k;
    // -----------------------------------------
               

    always @(posedge clk)
        if (rst) begin
            next_state <= 0;
            // =========================================
            // Обнулить счетчики
            k = 0;
            // -----------------------------------------
        end 
        else 
        begin
            // Автомат переходит в следующее состояние если: 
            // state = STOP (не ждем следующего символа, сразу выводим valid)
            // state = ERROR тут 2 случая: если в ошибку мы попали по недописанной строке, 
            //                             то нам не нужно ждать \0 так как по этому стопу 
            //                             мы в нее попали
            //                             если ошибка внутри строки нам нужно ждать \0, 
            //                             иначе мы стоповый байт примем за стартовый
            // valid = 1 Для всех остальных состояний автомата переход осуществляется 
            //           в зависимости от следующего символа, поэтому переходим только когда он принят
            if ((state == STOP)||valid||(state == ERROR))
            begin
                // =========================================
                // Логика счетчиков
                // СЧЕТЧИКИ СЧИТАЮТСЯ С 0, т.е. если вам нужно 2-3 символа, то 1 <= cnt <= 2 
                k <= (state == NUMBER) ? k + 1 : 0;
                // -----------------------------------------

                // Логика переходов
                case (state)
                    // Переходим из общих состояний
                    IDLE        : next_state <= start_stop ? START : IDLE;
                    START       : next_state <= 
                                                // =========================================
                                                // Стартовое условие (после \0)
                                                parentheses 
                                                // -----------------------------------------
                                                ? 4 : ERROR;
                    ERROR       : next_state <= (error_verify||(start_stop&&valid)) ? IDLE : ERROR;   
                    default     : next_state <= IDLE; // STOP ведет в IDLE

                    // =========================================
                    // Логика переходов автомата по варианту
                    PARENTHESES1: next_state <= math_symbol ? MATHSYMBOL : ERROR;
                    MATHSYMBOL: next_state <= number ? NUMBER : ERROR;
                    NUMBER: next_state <= (k == 1 && parentheses) ? PARENTHESES2 : (k == 0 && number) ? NUMBER : ERROR;
                    PARENTHESES2: next_state <= start_stop ? STOP : ERROR;
                    // -----------------------------------------

                endcase
            end
        end

endmodule

variants/lib/automat.v
//  Данный модуль работает на вывод информации, в нем ничего менять не нужно

module verify #(parameter UART_TX_baud, freq)  (
    input clk,
    input rst,
    input [7:0] ascii_char,
    input char_valid,
    output reg sequence_valid,
    output reg output_strobe
);
    wire    start_stop,         // Начало и конец строки (\0)
            small_letter,       // Строчная буква (a-z)
            capital_letter,     // Заглавная буква (A-Z)
            number,             // Цифра (0-9)
            hex_digit,          // Шестнадцатеричная цифра (0-9, A-F, a-f)
            punctuation_basic,  // Основные знаки препинания (., ,, :, ;, !, ?, ', ")
            punctuation_finance, // Финансовые символы (#, $, %, &, @)
            parentheses,        // Скобки ((, ), [, ])
            curly_braces,       // Фигурные скобки ({, }) - добавлено
            math_symbol,        // Математические символы (+, -, *, /, \, =, <, >)
            whitespace,         // Пробельные символы (пробел, табуляция, перевод строки, возврат каретки)
            vowel,              // Гласные буквы [aeiouAEIOU]
            consonant,          // Согласные буквы
            other;              // Другие символы

    localparam cnt_val = freq/UART_TX_baud + 1;
    reg [$clog2(freq/UART_TX_baud):0] strobe_cnt;
    reg strobe_clk;
    reg need_strobe_out;
    reg already_was;
    reg error_verify;

    
    reg [3:0] state;
    
    tsk prob(
        .state(state),
        .rst(rst),
        .clk(clk),
        .valid(char_valid),
        .next_state(state),
        .error_verify(error_verify),

        .start_stop(start_stop),                 // Начало и конец строки (\0)
        .small_letter(small_letter),             // Строчная буква (a-z)
        .capital_letter(capital_letter),         // Заглавная буква (A-Z)
        .number(number),                         // Цифра (0-9)
        .hex_digit(hex_digit),                   // Шестнадцатеричная цифра (0-9, A-F, a-f)
        .punctuation_basic(punctuation_basic),   // Основные знаки препинания (., ,, :, ;, !, ?, ', ")
        .punctuation_finance(punctuation_finance), // Финансовые символы (#, $, %, &, @)
        .parentheses(parentheses),               // Скобки ((, ), [, ])
        .curly_braces(curly_braces),             // Фигурные скобки ({, }) - добавлено
        .math_symbol(math_symbol),               // Математические символы (+, -, *, /, \, =, <, >)
        .whitespace(whitespace),                 // Пробельные символы (пробел, табуляция, перевод строки, возврат каретки)
        .vowel(vowel),                           // Гласные буквы [aeiouAEIOU]
        .consonant(consonant),                   // Согласные буквы
        .other(other)                            // Другое (подразумевается из строки 'other;')
    );


    ascii_type_detector ascii_detector(
        .ascii_char(ascii_char),
        .start_stop(start_stop),                 // Начало и конец строки (\0)
        .small_letter(small_letter),             // Строчная буква (a-z)
        .capital_letter(capital_letter),         // Заглавная буква (A-Z)
        .number(number),                         // Цифра (0-9)
        .hex_digit(hex_digit),                   // Шестнадцатеричная цифра (0-9, A-F, a-f)
        .punctuation_basic(punctuation_basic),   // Основные знаки препинания (., ,, :, ;, !, ?, ', ")
        .punctuation_finance(punctuation_finance), // Финансовые символы (#, $, %, &, @)
        .parentheses(parentheses),               // Скобки ((, ), [, ])
        .curly_braces(curly_braces),             // Фигурные скобки ({, }) - добавлено
        .math_symbol(math_symbol),               // Математические символы (+, -, *, /, \, =, <, >)
        .whitespace(whitespace),                 // Пробельные символы (пробел, табуляция, перевод строки, возврат каретки)
        .vowel(vowel),                           // Гласные буквы [aeiouAEIOU]
        .consonant(consonant),                   // Согласные буквы
        .other(other)                            // Другое (подразумевается из строки 'other;')
    );

    localparam IDLE =  4'b0000,
               START = 4'b0001,
               STOP =  4'b0010,
               ERROR = 4'b0011;

    always @(posedge clk)
        if (rst) begin
            strobe_clk <= 0;
            strobe_cnt <= cnt_val;
            sequence_valid <= 0;
            need_strobe_out <= 0;
            already_was <= 1;
            error_verify <= 0;
        end else begin
            strobe_cnt <= strobe_cnt - 1;
            strobe_clk <= 0;
            

            if (!strobe_cnt) 
            begin
                strobe_clk <= 1;
                strobe_cnt <= cnt_val;
            end
            if (state == ERROR && !already_was)
            begin
                need_strobe_out <= 1;
                already_was <= 1;
                error_verify <= start_stop;
            end
            if (state == IDLE && !already_was)
            begin
                need_strobe_out <= 1;
                sequence_valid <= 1;
                already_was <= 1;
            end
            if (state != ERROR && state != IDLE) 
                already_was <= 0;
            if (need_strobe_out && strobe_clk) 
            begin
                need_strobe_out <= 0;
                output_strobe <= 1;
                already_was <= 1;
            end 
            else 
                output_strobe <= 0;

            if (state != ERROR)
                error_verify <= 0;

            if (sequence_valid&&!need_strobe_out)
                sequence_valid <= 0;

        end
endmodule;

variants/v10/rk_test.v
// Модуль теста автомата
// Начиная с двойной черты ====== и заканчивая одинарной ------- идет код, 
// который необходимо заменить в соответствии с вариантом


module rk_test();

    // =========================================
    // Параметры тестирования
    // UART_RX_BAUD
    // UART_TX_baud
    // freq
    localparam UART_RX_BAUD = 20,
               UART_TX_baud = 20,
               freq = 200,
    // -----------------------------------------
               TR = freq/UART_RX_BAUD;
    
    
    reg clk = 0;
    reg rst;
    reg [7:0] ascii_char;
    reg ascii_valid;
    wire sequence_valid;
    wire output_strobe;
    
    always #1 clk = !clk;

    task cntclk(input [7:0] cnt);
        for (integer i = 0; i < cnt; i = i + 1) @(posedge clk);
    endtask
    
    task pch(input [7:0] putchar);
        begin
            ascii_char = putchar;
            cntclk(TR-1);
            ascii_valid = 1;
            cntclk(1);
            ascii_valid = 0;
        end
    endtask
    
    task transmit(input [100*8-1:0] str);
        begin
            integer i;
            integer len;
            len = 0;
            for (i = 0; i < 100; i = i + 1) begin
                if (str[8*i +: 8] != 0) begin
                    len = len + 1;
                end
            end
            pch(0);
            for (i = len-1; i >= 0; i = i - 1) begin
                pch(str[8*i +: 8]);
            end
            pch(0);
            cntclk(100);
        end
    endtask


    
    
    verify #(.UART_TX_baud(UART_TX_baud), .freq(freq)) 
        mverify (
        .clk(clk),
        .rst(rst),
        .ascii_char(ascii_char),
        .char_valid(ascii_valid),
        .sequence_valid(sequence_valid),
        .output_strobe(output_strobe)
    );

    initial begin
        $dumpvars;
        ascii_char = 0;
        ascii_valid = 0;
        rst = 1;
        cntclk(100);
        rst = 0;
        cntclk(100);
        // =========================================
        // transmit передает строку в виде \0 + параметр + \0 и делает небольшую задержку после
        // Для проверки автомата можно использовать одну правильную и одну неправильную последовательность
        transmit("(+12)");
        transmit("(+1A)");
        // -----------------------------------------
        cntclk(200);
        $finish;
    end
endmodule

variants/v10/dump.vcd
$date
	Sun Apr 27 19:30:11 2025
$end
$version
	Icarus Verilog
$end
$timescale
	1s
$end
$scope module rk_test $end
$var wire 1 ! sequence_valid $end
$var wire 1 " output_strobe $end
$var parameter 32 # TR $end
$var parameter 32 $ UART_RX_BAUD $end
$var parameter 32 % UART_TX_baud $end
$var parameter 32 & freq $end
$var reg 8 ' ascii_char [7:0] $end
$var reg 1 ( ascii_valid $end
$var reg 1 ) clk $end
$var reg 1 * rst $end
$scope module mverify $end
$var wire 8 + ascii_char [7:0] $end
$var wire 1 ( char_valid $end
$var wire 1 ) clk $end
$var wire 1 * rst $end
$var wire 1 , whitespace $end
$var wire 1 - vowel $end
$var wire 4 . state [3:0] $end
$var wire 1 / start_stop $end
$var wire 1 0 small_letter $end
$var wire 1 1 punctuation_finance $end
$var wire 1 2 punctuation_basic $end
$var wire 1 3 parentheses $end
$var wire 1 4 other $end
$var wire 1 5 number $end
$var wire 1 6 math_symbol $end
$var wire 1 7 hex_digit $end
$var wire 1 8 curly_braces $end
$var wire 1 9 consonant $end
$var wire 1 : capital_letter $end
$var parameter 4 ; ERROR $end
$var parameter 4 < IDLE $end
$var parameter 4 = START $end
$var parameter 4 > STOP $end
$var parameter 32 ? UART_TX_baud $end
$var parameter 33 @ cnt_val $end
$var parameter 32 A freq $end
$var reg 1 B already_was $end
$var reg 1 C error_verify $end
$var reg 1 D need_strobe_out $end
$var reg 1 " output_strobe $end
$var reg 1 ! sequence_valid $end
$var reg 1 E strobe_clk $end
$var reg 5 F strobe_cnt [4:0] $end
$scope module ascii_detector $end
$var wire 8 G ascii_char [7:0] $end
$var reg 1 : capital_letter $end
$var reg 1 9 consonant $end
$var reg 1 8 curly_braces $end
$var reg 1 7 hex_digit $end
$var reg 1 6 math_symbol $end
$var reg 1 5 number $end
$var reg 1 4 other $end
$var reg 1 3 parentheses $end
$var reg 1 2 punctuation_basic $end
$var reg 1 1 punctuation_finance $end
$var reg 1 0 small_letter $end
$var reg 1 / start_stop $end
$var reg 1 - vowel $end
$var reg 1 , whitespace $end
$upscope $end
$scope module prob $end
$var wire 1 : capital_letter $end
$var wire 1 ) clk $end
$var wire 1 9 consonant $end
$var wire 1 8 curly_braces $end
$var wire 1 C error_verify $end
$var wire 1 7 hex_digit $end
$var wire 1 6 math_symbol $end
$var wire 1 5 number $end
$var wire 1 4 other $end
$var wire 1 3 parentheses $end
$var wire 1 2 punctuation_basic $end
$var wire 1 1 punctuation_finance $end
$var wire 1 * rst $end
$var wire 1 0 small_letter $end
$var wire 1 / start_stop $end
$var wire 4 H state [3:0] $end
$var wire 1 ( valid $end
$var wire 1 - vowel $end
$var wire 1 , whitespace $end
$var parameter 32 I ERROR $end
$var parameter 32 J IDLE $end
$var parameter 32 K MATHSYMBOL $end
$var parameter 32 L NUMBER $end
$var parameter 32 M PARENTHESES1 $end
$var parameter 32 N PARENTHESES2 $end
$var parameter 32 O START $end
$var parameter 32 P STOP $end
$var reg 3 Q k [2:0] $end
$var reg 4 R next_state [3:0] $end
$upscope $end
$upscope $end
$scope task cntclk $end
$var reg 8 S cnt [7:0] $end
$scope begin $ivl_for_loop0 $end
$var integer 32 T i [31:0] $end
$upscope $end
$upscope $end
$scope task pch $end
$var reg 8 U putchar [7:0] $end
$upscope $end
$scope task transmit $end
$var reg 800 V str [799:0] $end
$scope begin $unm_blk_12 $end
$var integer 32 W i [31:0] $end
$var integer 32 X len [31:0] $end
$upscope $end
$upscope $end
$upscope $end
$enddefinitions $end
$comment Show the parameter values. $end
$dumpall
b10 P
b1 O
b111 N
b100 M
b110 L
b101 K
b0 J
b11 I
b11001000 A
b1011 @
b10100 ?
b10 >
b1 =
b0 <
b11 ;
b11001000 &
b10100 %
b10100 $
b1010 #
$end
#0
$dumpvars
bx X
bx W
bx V
bx U
b0 T
b1100100 S
bx R
bx Q
bx H
b0 G
bx F
xE
xD
xC
xB
0:
09
08
07
06
05
14
03
02
01
00
1/
bx .
0-
0,
b0 +
1*
0)
0(
b0 '
x"
x!
$end
#1
b0 .
b0 H
b0 R
0C
1B
0D
0!
b1011 F
0E
b0 Q
b1 T
1)
#2
0)
#3
b10 T
1)
#4
0)
#5
b11 T
1)
#6
0)
#7
b100 T
1)
#8
0)
#9
b101 T
1)
#10
0)
#11
b110 T
1)
#12
0)
#13
b111 T
1)
#14
0)
#15
b1000 T
1)
#16
0)
#17
b1001 T
1)
#18
0)
#19
b1010 T
1)
#20
0)
#21
b1011 T
1)
#22
0)
#23
b1100 T
1)
#24
0)
#25
b1101 T
1)
#26
0)
#27
b1110 T
1)
#28
0)
#29
b1111 T
1)
#30
0)
#31
b10000 T
1)
#32
0)
#33
b10001 T
1)
#34
0)
#35
b10010 T
1)
#36
0)
#37
b10011 T
1)
#38
0)
#39
b10100 T
1)
#40
0)
#41
b10101 T
1)
#42
0)
#43
b10110 T
1)
#44
0)
#45
b10111 T
1)
#46
0)
#47
b11000 T
1)
#48
0)
#49
b11001 T
1)
#50
0)
#51
b11010 T
1)
#52
0)
#53
b11011 T
1)
#54
0)
#55
b11100 T
1)
#56
0)
#57
b11101 T
1)
#58
0)
#59
b11110 T
1)
#60
0)
#61
b11111 T
1)
#62
0)
#63
b100000 T
1)
#64
0)
#65
b100001 T
1)
#66
0)
#67
b100010 T
1)
#68
0)
#69
b100011 T
1)
#70
0)
#71
b100100 T
1)
#72
0)
#73
b100101 T
1)
#74
0)
#75
b100110 T
1)
#76
0)
#77
b100111 T
1)
#78
0)
#79
b101000 T
1)
#80
0)
#81
b101001 T
1)
#82
0)
#83
b101010 T
1)
#84
0)
#85
b101011 T
1)
#86
0)
#87
b101100 T
1)
#88
0)
#89
b101101 T
1)
#90
0)
#91
b101110 T
1)
#92
0)
#93
b101111 T
1)
#94
0)
#95
b110000 T
1)
#96
0)
#97
b110001 T
1)
#98
0)
#99
b110010 T
1)
#100
0)
#101
b110011 T
1)
#102
0)
#103
b110100 T
1)
#104
0)
#105
b110101 T
1)
#106
0)
#107
b110110 T
1)
#108
0)
#109
b110111 T
1)
#110
0)
#111
b111000 T
1)
#112
0)
#113
b111001 T
1)
#114
0)
#115
b111010 T
1)
#116
0)
#117
b111011 T
1)
#118
0)
#119
b111100 T
1)
#120
0)
#121
b111101 T
1)
#122
0)
#123
b111110 T
1)
#124
0)
#125
b111111 T
1)
#126
0)
#127
b1000000 T
1)
#128
0)
#129
b1000001 T
1)
#130
0)
#131
b1000010 T
1)
#132
0)
#133
b1000011 T
1)
#134
0)
#135
b1000100 T
1)
#136
0)
#137
b1000101 T
1)
#138
0)
#139
b1000110 T
1)
#140
0)
#141
b1000111 T
1)
#142
0)
#143
b1001000 T
1)
#144
0)
#145
b1001001 T
1)
#146
0)
#147
b1001010 T
1)
#148
0)
#149
b1001011 T
1)
#150
0)
#151
b1001100 T
1)
#152
0)
#153
b1001101 T
1)
#154
0)
#155
b1001110 T
1)
#156
0)
#157
b1001111 T
1)
#158
0)
#159
b1010000 T
1)
#160
0)
#161
b1010001 T
1)
#162
0)
#163
b1010010 T
1)
#164
0)
#165
b1010011 T
1)
#166
0)
#167
b1010100 T
1)
#168
0)
#169
b1010101 T
1)
#170
0)
#171
b1010110 T
1)
#172
0)
#173
b1010111 T
1)
#174
0)
#175
b1011000 T
1)
#176
0)
#177
b1011001 T
1)
#178
0)
#179
b1011010 T
1)
#180
0)
#181
b1011011 T
1)
#182
0)
#183
b1011100 T
1)
#184
0)
#185
b1011101 T
1)
#186
0)
#187
b1011110 T
1)
#188
0)
#189
b1011111 T
1)
#190
0)
#191
b1100000 T
1)
#192
0)
#193
b1100001 T
1)
#194
0)
#195
b1100010 T
1)
#196
0)
#197
b1100011 T
1)
#198
0)
#199
0*
b0 T
1)
#200
0)
#201
0"
b1010 F
b1 T
1)
#202
0)
#203
b1001 F
b10 T
1)
#204
0)
#205
b1000 F
b11 T
1)
#206
0)
#207
b111 F
b100 T
1)
#208
0)
#209
b110 F
b101 T
1)
#210
0)
#211
b101 F
b110 T
1)
#212
0)
#213
b100 F
b111 T
1)
#214
0)
#215
b11 F
b1000 T
1)
#216
0)
#217
b10 F
b1001 T
1)
#218
0)
#219
b1 F
b1010 T
1)
#220
0)
#221
b0 F
b1011 T
1)
#222
0)
#223
1E
b1011 F
b1100 T
1)
#224
0)
#225
0E
b1010 F
b1101 T
1)
#226
0)
#227
b1001 F
b1110 T
1)
#228
0)
#229
b1000 F
b1111 T
1)
#230
0)
#231
b111 F
b10000 T
1)
#232
0)
#233
b110 F
b10001 T
1)
#234
0)
#235
b101 F
b10010 T
1)
#236
0)
#237
b100 F
b10011 T
1)
#238
0)
#239
b11 F
b10100 T
1)
#240
0)
#241
b10 F
b10101 T
1)
#242
0)
#243
b1 F
b10110 T
1)
#244
0)
#245
b0 F
b10111 T
1)
#246
0)
#247
1E
b1011 F
b11000 T
1)
#248
0)
#249
0E
b1010 F
b11001 T
1)
#250
0)
#251
b1001 F
b11010 T
1)
#252
0)
#253
b1000 F
b11011 T
1)
#254
0)
#255
b111 F
b11100 T
1)
#256
0)
#257
b110 F
b11101 T
1)
#258
0)
#259
b101 F
b11110 T
1)
#260
0)
#261
b100 F
b11111 T
1)
#262
0)
#263
b11 F
b100000 T
1)
#264
0)
#265
b10 F
b100001 T
1)
#266
0)
#267
b1 F
b100010 T
1)
#268
0)
#269
b0 F
b100011 T
1)
#270
0)
#271
1E
b1011 F
b100100 T
1)
#272
0)
#273
0E
b1010 F
b100101 T
1)
#274
0)
#275
b1001 F
b100110 T
1)
#276
0)
#277
b1000 F
b100111 T
1)
#278
0)
#279
b111 F
b101000 T
1)
#280
0)
#281
b110 F
b101001 T
1)
#282
0)
#283
b101 F
b101010 T
1)
#284
0)
#285
b100 F
b101011 T
1)
#286
0)
#287
b11 F
b101100 T
1)
#288
0)
#289
b10 F
b101101 T
1)
#290
0)
#291
b1 F
b101110 T
1)
#292
0)
#293
b0 F
b101111 T
1)
#294
0)
#295
1E
b1011 F
b110000 T
1)
#296
0)
#297
0E
b1010 F
b110001 T
1)
#298
0)
#299
b1001 F
b110010 T
1)
#300
0)
#301
b1000 F
b110011 T
1)
#302
0)
#303
b111 F
b110100 T
1)
#304
0)
#305
b110 F
b110101 T
1)
#306
0)
#307
b101 F
b110110 T
1)
#308
0)
#309
b100 F
b110111 T
1)
#310
0)
#311
b11 F
b111000 T
1)
#312
0)
#313
b10 F
b111001 T
1)
#314
0)
#315
b1 F
b111010 T
1)
#316
0)
#317
b0 F
b111011 T
1)
#318
0)
#319
1E
b1011 F
b111100 T
1)
#320
0)
#321
0E
b1010 F
b111101 T
1)
#322
0)
#323
b1001 F
b111110 T
1)
#324
0)
#325
b1000 F
b111111 T
1)
#326
0)
#327
b111 F
b1000000 T
1)
#328
0)
#329
b110 F
b1000001 T
1)
#330
0)
#331
b101 F
b1000010 T
1)
#332
0)
#333
b100 F
b1000011 T
1)
#334
0)
#335
b11 F
b1000100 T
1)
#336
0)
#337
b10 F
b1000101 T
1)
#338
0)
#339
b1 F
b1000110 T
1)
#340
0)
#341
b0 F
b1000111 T
1)
#342
0)
#343
1E
b1011 F
b1001000 T
1)
#344
0)
#345
0E
b1010 F
b1001001 T
1)
#346
0)
#347
b1001 F
b1001010 T
1)
#348
0)
#349
b1000 F
b1001011 T
1)
#350
0)
#351
b111 F
b1001100 T
1)
#352
0)
#353
b110 F
b1001101 T
1)
#354
0)
#355
b101 F
b1001110 T
1)
#356
0)
#357
b100 F
b1001111 T
1)
#358
0)
#359
b11 F
b1010000 T
1)
#360
0)
#361
b10 F
b1010001 T
1)
#362
0)
#363
b1 F
b1010010 T
1)
#364
0)
#365
b0 F
b1010011 T
1)
#366
0)
#367
1E
b1011 F
b1010100 T
1)
#368
0)
#369
0E
b1010 F
b1010101 T
1)
#370
0)
#371
b1001 F
b1010110 T
1)
#372
0)
#373
b1000 F
b1010111 T
1)
#374
0)
#375
b111 F
b1011000 T
1)
#376
0)
#377
b110 F
b1011001 T
1)
#378
0)
#379
b101 F
b1011010 T
1)
#380
0)
#381
b100 F
b1011011 T
1)
#382
0)
#383
b11 F
b1011100 T
1)
#384
0)
#385
b10 F
b1011101 T
1)
#386
0)
#387
b1 F
b1011110 T
1)
#388
0)
#389
b0 F
b1011111 T
1)
#390
0)
#391
1E
b1011 F
b1100000 T
1)
#392
0)
#393
0E
b1010 F
b1100001 T
1)
#394
0)
#395
b1001 F
b1100010 T
1)
#396
0)
#397
b1000 F
b1100011 T
1)
#398
0)
#399
b111 F
b1001 S
b0 U
b1100100 W
b101 X
b10100000101011001100010011001000101001 V
b0 T
1)
#400
0)
#401
b110 F
b1 T
1)
#402
0)
#403
b101 F
b10 T
1)
#404
0)
#405
b100 F
b11 T
1)
#406
0)
#407
b11 F
b100 T
1)
#408
0)
#409
b10 F
b101 T
1)
#410
0)
#411
b1 F
b110 T
1)
#412
0)
#413
b0 F
b111 T
1)
#414
0)
#415
1E
b1011 F
b1000 T
1)
#416
0)
#417
0E
b1010 F
b1 S
1(
b0 T
1)
#418
0)
#419
b1001 F
b1 .
b1 H
b1 R
13
04
0/
b1001 S
b101000 '
b101000 +
b101000 G
b101000 U
b100 W
0(
b0 T
1)
#420
0)
#421
0B
b1000 F
b1 T
1)
#422
0)
#423
b111 F
b10 T
1)
#424
0)
#425
b110 F
b11 T
1)
#426
0)
#427
b101 F
b100 T
1)
#428
0)
#429
b100 F
b101 T
1)
#430
0)
#431
b11 F
b110 T
1)
#432
0)
#433
b10 F
b111 T
1)
#434
0)
#435
b1 F
b1000 T
1)
#436
0)
#437
b0 F
b1 S
1(
b0 T
1)
#438
0)
#439
1E
b1011 F
b100 .
b100 H
b100 R
16
03
b1001 S
b101011 '
b101011 +
b101011 G
b101011 U
b11 W
0(
b0 T
1)
#440
0)
#441
0E
b1010 F
b1 T
1)
#442
0)
#443
b1001 F
b10 T
1)
#444
0)
#445
b1000 F
b11 T
1)
#446
0)
#447
b111 F
b100 T
1)
#448
0)
#449
b110 F
b101 T
1)
#450
0)
#451
b101 F
b110 T
1)
#452
0)
#453
b100 F
b111 T
1)
#454
0)
#455
b11 F
b1000 T
1)
#456
0)
#457
b10 F
b1 S
1(
b0 T
1)
#458
0)
#459
b1 F
b101 .
b101 H
b101 R
17
15
06
b1001 S
b110001 '
b110001 +
b110001 G
b110001 U
b10 W
0(
b0 T
1)
#460
0)
#461
b0 F
b1 T
1)
#462
0)
#463
1E
b1011 F
b10 T
1)
#464
0)
#465
0E
b1010 F
b11 T
1)
#466
0)
#467
b1001 F
b100 T
1)
#468
0)
#469
b1000 F
b101 T
1)
#470
0)
#471
b111 F
b110 T
1)
#472
0)
#473
b110 F
b111 T
1)
#474
0)
#475
b101 F
b1000 T
1)
#476
0)
#477
b100 F
b1 S
1(
b0 T
1)
#478
0)
#479
b11 F
b110 .
b110 H
b110 R
17
15
b1001 S
b110010 '
b110010 +
b110010 G
b110010 U
b1 W
0(
b0 T
1)
#480
0)
#481
b10 F
b1 T
1)
#482
0)
#483
b1 F
b10 T
1)
#484
0)
#485
b0 F
b11 T
1)
#486
0)
#487
1E
b1011 F
b100 T
1)
#488
0)
#489
0E
b1010 F
b101 T
1)
#490
0)
#491
b1001 F
b110 T
1)
#492
0)
#493
b1000 F
b111 T
1)
#494
0)
#495
b111 F
b1000 T
1)
#496
0)
#497
b110 F
b1 S
1(
b0 T
1)
#498
0)
#499
b101 F
b1 Q
13
07
05
b1001 S
b101001 '
b101001 +
b101001 G
b101001 U
b0 W
0(
b0 T
1)
#500
0)
#501
b100 F
b1 T
1)
#502
0)
#503
b11 F
b10 T
1)
#504
0)
#505
b10 F
b11 T
1)
#506
0)
#507
b1 F
b100 T
1)
#508
0)
#509
b0 F
b101 T
1)
#510
0)
#511
1E
b1011 F
b110 T
1)
#512
0)
#513
0E
b1010 F
b111 T
1)
#514
0)
#515
b1001 F
b1000 T
1)
#516
0)
#517
b1000 F
b1 S
1(
b0 T
1)
#518
0)
#519
b111 F
b111 .
b111 H
b111 R
b10 Q
1/
14
03
b1001 S
b0 '
b0 +
b0 G
b0 U
b11111111111111111111111111111111 W
0(
b0 T
1)
#520
0)
#521
b110 F
b1 T
1)
#522
0)
#523
b101 F
b10 T
1)
#524
0)
#525
b100 F
b11 T
1)
#526
0)
#527
b11 F
b100 T
1)
#528
0)
#529
b10 F
b101 T
1)
#530
0)
#531
b1 F
b110 T
1)
#532
0)
#533
b0 F
b111 T
1)
#534
0)
#535
1E
b1011 F
b1000 T
1)
#536
0)
#537
0E
b1010 F
b1 S
1(
b0 T
1)
#538
0)
#539
b1001 F
b10 .
b10 H
b10 R
b0 Q
b1100100 S
0(
b0 T
1)
#540
0)
#541
b0 .
b0 H
b0 R
b1000 F
b1 T
1)
#542
0)
#543
1B
1!
1D
b111 F
b10 T
1)
#544
0)
#545
b110 F
b11 T
1)
#546
0)
#547
b101 F
b100 T
1)
#548
0)
#549
b100 F
b101 T
1)
#550
0)
#551
b11 F
b110 T
1)
#552
0)
#553
b10 F
b111 T
1)
#554
0)
